{
  "20150510_085326": {
    "input": {
      "parameters": {
        "spreadThreshold": 1.0,
        "orderSize": 100
      },
      "strategy": "weighted_price"
    },
    "result": {
      "id": "20150510_085326",
      "position": {
        "current": 200,
        "min": -100,
        "max": 200
      },
      "balance": {
        "current": -2496.0,
        "min": -2496.0,
        "max": 1251.0
      },
      "pnl": {
        "current": 10.0,
        "min": -24.0,
        "max": 18.0
      },
      "trades": 4,
      "timestamp": "20150510_085330",
      "duration_ms": 1181
    },
    "resultGraphs": ["pnl", "position"]
  }
}